wtf_mul/__init__.py
wtf_mul/mul.py
wtf_mul-0.2.0.dist-info/METADATA
wtf_mul-0.2.0.dist-info/WHEEL
wtf_mul-0.2.0.dist-info/entry_points.txt
wtf_mul-0.2.0.dist-info/top_level.txt
wtf_mul-0.2.0.dist-info/RECORD
